{"cameraMode":{"drawMode":0,"name":"Shaded","section":"Shading Mode"},"sceneLighting":true,"audioPlay":false,"sceneViewState":{"m_AlwaysRefresh":false,"showFog":true,"showSkybox":true,"showFlares":true,"showImageEffects":true,"showParticleSystems":true,"showVisualEffectGraphs":true,"m_FxEnabled":true},"in2DMode":false,"pivot":{"x":0.46041393280029299,"y":-2.527761459350586,"z":-0.5815682411193848},"rotation":{"x":0.2769099771976471,"y":0.6012987494468689,"z":-0.2338070571422577,"w":0.7122783064842224},"size":5.486485958099365,"orthographic":false}